README.rst
setup.cfg
setup.py
erratum/__init__.py
erratum/document.py
erratum/error.py
erratum/format.py
erratum/version.py
erratum.egg-info/PKG-INFO
erratum.egg-info/SOURCES.txt
erratum.egg-info/dependency_links.txt
erratum.egg-info/entry_points.txt
erratum.egg-info/not-zip-safe
erratum.egg-info/top_level.txt